ZmqZhinan/README.md
ZmqZhinan/__init__.py
ZmqZhinan/__main__.py
ZmqZhinan/file.epub
ZmqZhinan/index.html
ZmqZhinan/css/__init__.py
ZmqZhinan/css/annotations.css
ZmqZhinan/css/main.css
ZmqZhinan/css/normalize.css
ZmqZhinan/css/popup.css
ZmqZhinan/font/__init__.py
ZmqZhinan/font/fontello.eot
ZmqZhinan/font/fontello.svg
ZmqZhinan/font/fontello.ttf
ZmqZhinan/font/fontello.woff
ZmqZhinan/img/__init__.py
ZmqZhinan/img/annotator-glyph-sprite.png
ZmqZhinan/img/annotator-icon-sprite.png
ZmqZhinan/img/apple-touch-icon.png
ZmqZhinan/img/cancelfullscreen.png
ZmqZhinan/img/close.png
ZmqZhinan/img/fullscreen.png
ZmqZhinan/img/loader.gif
ZmqZhinan/img/menu-icon.png
ZmqZhinan/img/save.png
ZmqZhinan/img/saved.png
ZmqZhinan/img/settings-s.png
ZmqZhinan/img/settings.png
ZmqZhinan/img/star.png
ZmqZhinan/js/__init__.py
ZmqZhinan/js/epub.js
ZmqZhinan/js/epub.min.js
ZmqZhinan/js/epub.min.map
ZmqZhinan/js/hooks.min.js
ZmqZhinan/js/hooks.min.map
ZmqZhinan/js/reader.js
ZmqZhinan/js/reader.js.map
ZmqZhinan/js/reader.min.js
ZmqZhinan/js/reader.min.map
ZmqZhinan/js/hooks/__init__.py
ZmqZhinan/js/hooks/extensions/__init__.py
ZmqZhinan/js/hooks/extensions/highlight.js
ZmqZhinan/js/libs/__init__.py
ZmqZhinan/js/libs/jquery.min.js
ZmqZhinan/js/libs/localforage.min.js
ZmqZhinan/js/libs/screenfull.js
ZmqZhinan/js/libs/screenfull.min.js
ZmqZhinan/js/libs/zip.min.js
ZmqZhinan/js/plugins/__init__.py
ZmqZhinan/js/plugins/hypothesis.js
ZmqZhinan/js/plugins/search.js
zmq_zhinan-2024.3.2.0.dist-info/METADATA
zmq_zhinan-2024.3.2.0.dist-info/WHEEL
zmq_zhinan-2024.3.2.0.dist-info/entry_points.txt
zmq_zhinan-2024.3.2.0.dist-info/top_level.txt
zmq_zhinan-2024.3.2.0.dist-info/RECORD
